recoverpy/__init__.py
recoverpy/__main__.py
recoverpy/lib/env_check.py
recoverpy/lib/helper.py
recoverpy/lib/lsblk.py
recoverpy/lib/saver.py
recoverpy/lib/search/progress_monitoring.py
recoverpy/lib/search/search_engine.py
recoverpy/lib/search/thread_factory.py
recoverpy/log/logger.py
recoverpy/models/grep_result.py
recoverpy/models/partition.py
recoverpy/models/search_params.py
recoverpy/models/search_progress.py
recoverpy/ui/__init__.py
recoverpy/ui/app.py
recoverpy/ui/css/__init__.py
recoverpy/ui/css/screen-modal.css
recoverpy/ui/css/screen-params.css
recoverpy/ui/css/screen-path-edit.css
recoverpy/ui/css/screen-result.css
recoverpy/ui/css/screen-save.css
recoverpy/ui/css/screen-search.css
recoverpy/ui/screens/__init__.py
recoverpy/ui/screens/modal.py
recoverpy/ui/screens/screen_params.py
recoverpy/ui/screens/screen_path_edit.py
recoverpy/ui/screens/screen_result.py
recoverpy/ui/screens/screen_save.py
recoverpy/ui/screens/screen_search.py
recoverpy/ui/widgets/directory_tree.py
recoverpy/ui/widgets/grep_result_list.py
recoverpy/ui/widgets/partition_list.py
recoverpy-2.2.1.dist-info/METADATA
recoverpy-2.2.1.dist-info/WHEEL
recoverpy-2.2.1.dist-info/entry_points.txt
recoverpy-2.2.1.dist-info/licenses/LICENSE
recoverpy-2.2.1.dist-info/RECORD
