Metadata-Version: 2.4
Name: recoverpy
Version: 2.2.1
Summary: A TUI to recover overwritten or deleted data.
Project-URL: homepage, https://github.com/PabloLec/recoverpy
Project-URL: repository, https://github.com/PabloLec/recoverpy
Project-URL: documentation, https://github.com/PabloLec/recoverpy#readme
Author-email: PabloLec <pablolec@pm.me>
License: GPL-3.0 License
License-File: LICENSE
Keywords: async,asyncio,cli,console,cui,cybersec,cybersecurity,data,data recovery,data recovery tool,education,forensic,forensics,grep,hack,hacking,learn,linux,ncurses,pentest,pentesting,recovery,search,security,teach,teaching,terminal,textual,training,tui,unix
Classifier: Development Status :: 5 - Production/Stable
Classifier: Environment :: Console
Classifier: Environment :: Console :: Curses
Classifier: Framework :: AsyncIO
Classifier: Intended Audience :: Developers
Classifier: Intended Audience :: Education
Classifier: Intended Audience :: End Users/Desktop
Classifier: Intended Audience :: Information Technology
Classifier: Intended Audience :: System Administrators
Classifier: License :: OSI Approved :: GNU General Public License v3 (GPLv3)
Classifier: Operating System :: POSIX :: Linux
Classifier: Programming Language :: Python :: 3.8
Classifier: Programming Language :: Python :: 3.9
Classifier: Programming Language :: Python :: 3.10
Classifier: Programming Language :: Python :: 3.11
Classifier: Programming Language :: Python :: 3.12
Classifier: Programming Language :: Python :: 3.13
Classifier: Topic :: Security
Classifier: Topic :: System :: Archiving :: Backup
Classifier: Topic :: System :: Filesystems
Classifier: Topic :: System :: Recovery Tools
Classifier: Topic :: System :: Shells
Classifier: Topic :: System :: Systems Administration
Classifier: Topic :: Terminals
Classifier: Topic :: Utilities
Classifier: Typing :: Typed
Requires-Python: <4.0.0,>=3.8.1
Requires-Dist: textual==3.0.1
